scsprox/__init__.py
scsprox/examples.py
scsprox/prox_obj.py
scsprox/scs_mapping.py
scsprox/scsprox.py
scsprox/timer.py
scsprox/verify.py
scsprox/test/test_admmwrapper.py
scsprox/test/test_memory.py
scsprox/test/test_prox_obj.py
scsprox/test/test_scs_mapping.py
scsprox/test/test_sol_extract.py
scsprox/test/test_top_level.py
scsprox-0.1.0a2.dist-info/DESCRIPTION.rst
scsprox-0.1.0a2.dist-info/METADATA
scsprox-0.1.0a2.dist-info/RECORD
scsprox-0.1.0a2.dist-info/WHEEL
scsprox-0.1.0a2.dist-info/metadata.json
scsprox-0.1.0a2.dist-info/top_level.txt
